globus_compute_common/__init__.py
globus_compute_common/globus_compute_flake8.py
globus_compute_common/py.typed
globus_compute_common/pydantic_v1.py
globus_compute_common/redis_endpoint_lock.py
globus_compute_common/redis_task.py
globus_compute_common/sdk_version_sharing.py
globus_compute_common/testing.py
globus_compute_common/messagepack/__init__.py
globus_compute_common/messagepack/exceptions.py
globus_compute_common/messagepack/packer.py
globus_compute_common/messagepack/protocol.py
globus_compute_common/messagepack/message_types/__init__.py
globus_compute_common/messagepack/message_types/base.py
globus_compute_common/messagepack/message_types/container.py
globus_compute_common/messagepack/message_types/ep_status_report.py
globus_compute_common/messagepack/message_types/manager_status_report.py
globus_compute_common/messagepack/message_types/result.py
globus_compute_common/messagepack/message_types/task.py
globus_compute_common/messagepack/message_types/task_cancel.py
globus_compute_common/messagepack/message_types/task_transition.py
globus_compute_common/messagepack/protocol_versions/__init__.py
globus_compute_common/messagepack/protocol_versions/proto1.py
globus_compute_common/redis/__init__.py
globus_compute_common/redis/connection.py
globus_compute_common/redis/fields.py
globus_compute_common/redis/pubsub.py
globus_compute_common/redis/serde.py
globus_compute_common/redis/task_queue.py
globus_compute_common/task_storage/__init__.py
globus_compute_common/task_storage/base.py
globus_compute_common/task_storage/default_storage.py
globus_compute_common/task_storage/redis.py
globus_compute_common/task_storage/s3.py
globus_compute_common/tasks/__init__.py
globus_compute_common/tasks/constants.py
globus_compute_common/tasks/protocol.py
globus_compute_common-0.7.1.dist-info/licenses/LICENSE
globus_compute_common-0.7.1.dist-info/METADATA
globus_compute_common-0.7.1.dist-info/WHEEL
globus_compute_common-0.7.1.dist-info/top_level.txt
globus_compute_common-0.7.1.dist-info/RECORD
