Metadata-Version: 2.4
Name: globus-compute-common
Version: 0.7.1
Summary: Common tools for Globus Compute projects
Home-page: https://github.com/globus/globus-compute-common
Author: Globus Team
Author-email: support@globus.org
Classifier: Development Status :: 3 - Alpha
Classifier: Intended Audience :: Developers
Classifier: License :: OSI Approved :: Apache Software License
Classifier: Programming Language :: Python :: 3
Requires-Python: >=3.9
License-File: LICENSE
Requires-Dist: pydantic<3,>=1
Provides-Extra: dev
Requires-Dist: pytest<9; extra == "dev"
Requires-Dist: pytest-cov<7; extra == "dev"
Requires-Dist: pytest-xdist<4; extra == "dev"
Requires-Dist: types-redis; extra == "dev"
Provides-Extra: moto
Requires-Dist: moto[s3]<6; extra == "moto"
Provides-Extra: redis
Requires-Dist: redis<7,>=5.3; extra == "redis"
Provides-Extra: boto3
Requires-Dist: boto3>=1.37; extra == "boto3"
Dynamic: license-file
